odoo/__init__.py
odoo/_account_account.py
odoo/_account_invoice.py
odoo/_account_journal.py
odoo/_account_move.py
odoo/_account_tax.py
odoo/_analytic_account.py
odoo/_company.py
odoo/_country.py
odoo/_crm_tag.py
odoo/_generic.py
odoo/_integration.py
odoo/_ir_attachment.py
odoo/_mail_message.py
odoo/_partner.py
odoo/_partner_category.py
odoo/_payment_term.py
odoo/_product.py
odoo/_product_category.py
odoo/_product_template.py
odoo/_purchase_order.py
odoo/_sale_order.py
odoo/_stock.py
odoo/_user.py
odoo/exceptions.py
odoo_py-0.0.19.dist-info/licenses/LICENSE
odoo_py-0.0.19.dist-info/METADATA
odoo_py-0.0.19.dist-info/WHEEL
odoo_py-0.0.19.dist-info/top_level.txt
odoo_py-0.0.19.dist-info/RECORD
