Metadata-Version: 2.4
Name: odoo_py
Version: 0.0.19
Summary: Package to abstract the Odoo API
Home-page: https://github.com/IT-NOSSA-FARMACIA/odoo-py
Author: Rafael Galleani
Author-email: Rafael Galleani <rafegal@gmail.com>
Project-URL: Homepage, https://github.com/IT-NOSSA-FARMACIA/odoo-py
Project-URL: Issues, https://github.com/IT-NOSSA-FARMACIA/odoo-py
Classifier: Programming Language :: Python :: 3
Classifier: License :: OSI Approved :: MIT License
Classifier: Operating System :: OS Independent
Requires-Python: >=3.9
License-File: LICENSE
Requires-Dist: environs>=9.5.0
Dynamic: author
Dynamic: home-page
Dynamic: license-file
Dynamic: requires-python
